esp_gen.cpython-310-darwin.so
cgbind/__init__.py
cgbind/add_substrate.py
cgbind/architectures.py
cgbind/atoms.py
cgbind/bonds.py
cgbind/build.py
cgbind/cage.py
cgbind/cage_subt.py
cgbind/calculations.py
cgbind/config.py
cgbind/constants.py
cgbind/esp.py
cgbind/exceptions.py
cgbind/geom.py
cgbind/input_output.py
cgbind/linker.py
cgbind/log.py
cgbind/molecule.py
cgbind/substrate.py
cgbind/templates.py
cgbind/utils.py
cgbind/x_motifs.py
cgbind/ext/__init__.py
cgbind/ext/esp_gen.pyx
cgbind/lib/m12l24.obj
cgbind/lib/m2l4.obj
cgbind/lib/m4l6.obj
cgbind/lib/m4l6n.obj
cgbind/lib/m4l6t.obj
cgbind/lib/m6l8.obj
cgbind-1.0.4.dist-info/LICENSE.md
cgbind-1.0.4.dist-info/METADATA
cgbind-1.0.4.dist-info/WHEEL
cgbind-1.0.4.dist-info/top_level.txt
cgbind-1.0.4.dist-info/RECORD
